fuzzycategory/__init__.py
fuzzycategory-0.0.4.dist-info/DESCRIPTION.rst
fuzzycategory-0.0.4.dist-info/METADATA
fuzzycategory-0.0.4.dist-info/RECORD
fuzzycategory-0.0.4.dist-info/WHEEL
fuzzycategory-0.0.4.dist-info/metadata.json
fuzzycategory-0.0.4.dist-info/top_level.txt
